README.rst
net.py
setup.py
speeder.egg-info/PKG-INFO
speeder.egg-info/SOURCES.txt
speeder.egg-info/dependency_links.txt
speeder.egg-info/entry_points.txt
speeder.egg-info/requires.txt
speeder.egg-info/top_level.txt