Metadata-Version: 1.1
Name: speeder
Version: 0.0.4
Summary: Debian Net Speeder 
Home-page: https://github.com/gkdeveloper/speeder
Author: Gaurav Kumar Verma
Author-email: gkverma1094@gmail.com
License: GNU
Keywords: Debain,Internet speed
Platform: UNKNOWN
Classifier: Development Status :: 4 - Beta
Classifier: Programming Language :: Python
Classifier: Environment :: Console
Classifier: Operating System :: OS Independent
Classifier: Programming Language :: Python :: 2
Classifier: Programming Language :: Python :: 3
